torchmd_cg/__init__.py
torchmd_cg/utils/__init__.py
torchmd_cg/utils/make_deltaforces.py
torchmd_cg/utils/mappings.py
torchmd_cg/utils/prior_fit.py
torchmd_cg/utils/psfwriter.py
torchmd_cg-0.0.2.dist-info/LICENSE
torchmd_cg-0.0.2.dist-info/METADATA
torchmd_cg-0.0.2.dist-info/WHEEL
torchmd_cg-0.0.2.dist-info/top_level.txt
torchmd_cg-0.0.2.dist-info/RECORD
