Metadata-Version: 2.1
Name: torchmd-cg
Version: 0.0.2
Summary: TorchMD-CG. Coarse Grained molecular dynamics with pytorch
Home-page: https://github.com/torchmd/torchmd_cg/
Author: Acellera
Author-email: info@acellera.com
License: UNKNOWN
Platform: UNKNOWN
Classifier: Programming Language :: Python :: 3
Classifier: Operating System :: POSIX :: Linux
Classifier: License :: OSI Approved :: MIT License
License-File: LICENSE
Requires-Dist: torchmd
Requires-Dist: schnetpack
